invisible_hand/__init__.py
invisible_hand/__main__.py
invisible_hand/cli.py
invisible_hand/config/__init__.py
invisible_hand/config/base_config.py
invisible_hand/config/cmd.py
invisible_hand/config/config_manager.py
invisible_hand/config/context.py
invisible_hand/config/export_toml.py
invisible_hand/config/words.py
invisible_hand/core/__init__.py
invisible_hand/core/console_color.py
invisible_hand/ensures.py
invisible_hand/errors.py
invisible_hand/scripts/__init__.py
invisible_hand/scripts/add_students.py
invisible_hand/scripts/announce_grade.py
invisible_hand/scripts/crawl_classroom.py
invisible_hand/scripts/dev.py
invisible_hand/scripts/event_times.py
invisible_hand/scripts/grant_read_access.py
invisible_hand/scripts/patch_project.py
invisible_hand/scripts/shared_options/__init__.py
invisible_hand/urls.py
invisible_hand/utils/__init__.py
invisible_hand/utils/github_entities.py
invisible_hand/utils/github_scanner.py
invisible_hand/utils/google_student.py
invisible_hand-0.3.1.dist-info/entry_points.txt
invisible_hand-0.3.1.dist-info/LICENSE
invisible_hand-0.3.1.dist-info/WHEEL
invisible_hand-0.3.1.dist-info/METADATA
invisible_hand-0.3.1.dist-info/RECORD
